Metadata-Version: 2.1
Name: sudoku-sat
Version: 1.0.0
Summary: Solve and generate basic Sudokus and Sudokus with an extended set of rules.
Home-page: https://github.com/charludo/sudoku-sat
Author: Charlotte Hartmann Paludo
Author-email: charlotte.hartmann-paludo@stud.uni-due.de
License: UNKNOWN
Keywords: sudoku,sat
Platform: UNKNOWN
